spm_tools/__init__.py
spm_tools/_uniform_coords.py
spm_tools/_version.py
spm_tools/io.py
spm_tools/level.py
spm_tools/profile.py
spm_tools/scanline.py
spm_tools/utilities.py
spm_tools/example_data/__init__.py
spm_tools/example_data/synthetic.py
spm_tools-0.1.1.dist-info/LICENSE
spm_tools-0.1.1.dist-info/METADATA
spm_tools-0.1.1.dist-info/WHEEL
spm_tools-0.1.1.dist-info/top_level.txt
spm_tools-0.1.1.dist-info/RECORD
